hardware/wk7/example/verilog/sram_128b_w2048.v
// Created by prof. Mingu Kang @VVIP Lab in UCSD ECE department
// Please do not spread this code without permission 
module sram_128b_w2048 (CLK, D, Q, CEN, WEN, A);

  input  CLK;
  input  WEN;
  input  CEN;
  input  [127:0] D;
  input  [10:0] A;
  output [127:0] Q;
  parameter num = 2048;

  reg [127:0] memory [num-1:0];
  reg [10:0] add_q;
  assign Q = memory[add_q];

  always @ (posedge CLK) begin

   if (!CEN && WEN) // read 
      add_q <= A;
   if (!CEN && !WEN) // write
      memory[A] <= D; 

  end

endmodule

hardware/wk7/example/verilog/sram_tb.v
// Created by prof. Mingu Kang @VVIP Lab in UCSD ECE department
// Please do not spread this code without permission 

`timescale 1 ns/1 ps

module sram_tb;


`define NULL 0

reg CLK = 0;
reg [10:0]  A = 0;
reg [127:0] D = 0;
reg CEN_EXT = 0;
reg CEN_Q ;
reg WEN_EXT = 1;
reg WEN_Q ;
wire [127:0] Q;


sram_128b_w2048 sram_instance (
	.CLK(CLK), 
	.CEN(CEN_Q), 
	.WEN(WEN_Q),
        .A(A), 
        .D(D), 
        .Q(Q));


initial begin 

  $dumpfile("sram_tb.vcd");
  $dumpvars(0,sram_tb);

    #20 CLK = 1'b1;  
 
    #20 CLK = 1'b0;  A = 11'b00000000000; D = 128'hFFFFFFFFFFFFFFFFFFFFFFFFFFFFFFFF; WEN_EXT = 0;

    #20 CLK = 1'b1;  
  
    #20 CLK = 1'b0;  A = 11'b00000000010; D = 128'hEEEEEEEEEEEEEEEEEEEEEEEEEEEEEEEE; WEN_EXT = 1;

    #20 CLK = 1'b1;   

    #20 CLK = 1'b0;  A = 11'b00000000001;

    #20 CLK = 1'b1;  

    #20 CLK = 1'b0;  A = 11'b00000000010;

    #20 CLK = 1'b1;  

    #20 CLK = 1'b0;  CEN_EXT = 1;

    #20 CLK = 1'b1;

    #20 CLK = 1'b0;

  #10 $finish;


end

 always @ (posedge CLK) begin
   WEN_Q <= WEN_EXT;
   CEN_Q <= CEN_EXT;
 end

endmodule

hardware/wk7/example/sram_tb.vcd
$date
	Sun Sep  5 23:03:49 2021
$end
$version
	Icarus Verilog
$end
$timescale
	1ps
$end
$scope module sram_tb $end
$var wire 128 ! Q [127:0] $end
$var reg 11 " A [10:0] $end
$var reg 1 # CEN_EXT $end
$var reg 1 $ CEN_Q $end
$var reg 1 % CLK $end
$var reg 128 & D [127:0] $end
$var reg 1 ' WEN_EXT $end
$var reg 1 ( WEN_Q $end
$scope module sram_instance $end
$var wire 11 ) A [10:0] $end
$var wire 1 $ CEN $end
$var wire 1 % CLK $end
$var wire 128 * D [127:0] $end
$var wire 128 + Q [127:0] $end
$var wire 1 ( WEN $end
$var reg 11 , add_q [10:0] $end
$upscope $end
$upscope $end
$enddefinitions $end
#0
$dumpvars
bx ,
bx +
b0 *
b0 )
x(
1'
b0 &
0%
x$
0#
b0 "
bx !
$end
#20000
0$
1(
1%
#40000
0'
b11111111111111111111111111111111111111111111111111111111111111111111111111111111111111111111111111111111111111111111111111111111 &
b11111111111111111111111111111111111111111111111111111111111111111111111111111111111111111111111111111111111111111111111111111111 *
0%
#60000
0(
b0 ,
1%
#80000
1'
b11101110111011101110111011101110111011101110111011101110111011101110111011101110111011101110111011101110111011101110111011101110 &
b11101110111011101110111011101110111011101110111011101110111011101110111011101110111011101110111011101110111011101110111011101110 *
b10 "
b10 )
0%
#100000
1(
1%
#120000
b1 "
b1 )
0%
#140000
b1 ,
1%
#160000
b10 "
b10 )
0%
#180000
b11101110111011101110111011101110111011101110111011101110111011101110111011101110111011101110111011101110111011101110111011101110 !
b11101110111011101110111011101110111011101110111011101110111011101110111011101110111011101110111011101110111011101110111011101110 +
b10 ,
1%
#200000
1#
0%
#220000
1$
1%
